geounit/__init__.py
geounit/geounit.py
geounit-1.0.1.dist-info/licenses/LICENSE
geounit-1.0.1.dist-info/METADATA
geounit-1.0.1.dist-info/WHEEL
geounit-1.0.1.dist-info/top_level.txt
geounit-1.0.1.dist-info/RECORD
