Metadata-Version: 2.4
Name: geounit
Version: 1.0.1
Summary: Geometric units conversions made easy
Home-page: https://github.com/unkaktus/geounit
Author: Ivan Markin
Author-email: git@unkaktus.art
License: MIT
Classifier: Programming Language :: Python :: 3
Classifier: License :: OSI Approved :: MIT License
Classifier: Operating System :: OS Independent
Requires-Python: >=3.7
License-File: LICENSE
Requires-Dist: astropy
Dynamic: license-file
